lvpyio_wrapped/__init__.py
lvpyio_wrapped/chunkify.py
lvpyio_wrapped/client/__init__.py
lvpyio_wrapped/client/buffer.py
lvpyio_wrapped/client/particles.py
lvpyio_wrapped/client/send_command.py
lvpyio_wrapped/client/set.py
lvpyio_wrapped/service/__init__.py
lvpyio_wrapped/service/__main__.py
lvpyio_wrapped/service/commands.py
lvpyio_wrapped-1.3.1.dist-info/LICENSE.txt
lvpyio_wrapped-1.3.1.dist-info/METADATA
lvpyio_wrapped-1.3.1.dist-info/WHEEL
lvpyio_wrapped-1.3.1.dist-info/top_level.txt
lvpyio_wrapped-1.3.1.dist-info/RECORD
