Metadata-Version: 2.1
Name: lvpyio_wrapped
Version: 1.3.1
Summary: Wrapper around lvpyio, a reader/writer for DaVis images, vector fields, and particle fields
Home-page: https://www.lavision.de/
Author: LaVision GmbH
Author-email: python@lavision.de
License: Free To Use But Restricted
Platform: Windows
Platform: Linux
License-File: ../lvpyio/LICENSE.txt
Requires-Dist: lvpyio==1.3.1
Requires-Dist: pyzmq>=19.0.1
Requires-Dist: psutil>=5.8.0
Provides-Extra: plotting
Requires-Dist: matplotlib>=3.2.1; extra == "plotting"
